gif_me_loader/__init__.py
gif_me_loader-0.0.1.dist-info/LICENSE
gif_me_loader-0.0.1.dist-info/METADATA
gif_me_loader-0.0.1.dist-info/WHEEL
gif_me_loader-0.0.1.dist-info/top_level.txt
gif_me_loader-0.0.1.dist-info/RECORD
